hffe/__init__.py
hffe/bigplot.py
hffe/options.py
hffe/parsers.py
hffe/stock.py
hffe/utilities.py
hffe/volatility.py
hffe-0.0.13.dist-info/LICENSE.txt
hffe-0.0.13.dist-info/METADATA
hffe-0.0.13.dist-info/WHEEL
hffe-0.0.13.dist-info/top_level.txt
hffe-0.0.13.dist-info/RECORD
