Metadata-Version: 2.1
Name: hffe
Version: 0.0.13
Summary: Implements high-frequency financial econometrics tools.
Home-page: http://github.com/salompas/hffe
Author: Guilherme Salome
Author-email: guilhermesalome@gmail.com
License: MIT
Platform: UNKNOWN
Classifier: Programming Language :: Python :: 3.6
Classifier: License :: OSI Approved :: GNU General Public License v3 (GPLv3)
Classifier: Operating System :: OS Independent
Classifier: Development Status :: 1 - Planning
Requires-Dist: numpy (>=1.15.0)
Requires-Dist: pandas (>=0.23.0)
Requires-Dist: matplotlib (>=3.0.0)
